caixa/__init__.py
caixa/gsc/__init__.py
caixa/gsc/chamado.py
caixa/gsc/log_settings.py
caixa/gsc/webservice.py
caixa.gsc-0.2.1.dist-info/METADATA
caixa.gsc-0.2.1.dist-info/WHEEL
caixa.gsc-0.2.1.dist-info/top_level.txt
caixa.gsc-0.2.1.dist-info/RECORD
