Metadata-Version: 2.1
Name: caixa.gsc
Version: 0.2.1
Summary: Biblioteca de comunicação com os webservices de Gerenciamento de Serviços da Caixa Econômica
Home-page: https://github.com/claytonaalves/caixa.gsc
Author: Clayton A. Alves
Author-email: clayton.aa@gmail.com
License: UNKNOWN
Platform: UNKNOWN
Classifier: Development Status :: 4 - Beta
Classifier: Programming Language :: Python :: 3.6
Classifier: License :: OSI Approved :: MIT License
Classifier: Operating System :: OS Independent
Requires-Dist: requests (>=2.19.1)
Requires-Dist: zeep (>=3.1.0)
